LICENSE
MANIFEST.in
README.md
setup.py
deahub/CCR.py
deahub/CCR_pyomo.py
deahub/DDF.py
deahub/DDF_pyomo.py
deahub/SBM.py
deahub/SBM_pyomo.py
deahub/Ui_table.py
deahub/__init__.py
deahub/__main__.py
deahub/deasolver.py
deahub/run.py
deahub.egg-info/PKG-INFO
deahub.egg-info/SOURCES.txt
deahub.egg-info/dependency_links.txt
deahub.egg-info/entry_points.txt
deahub.egg-info/requires.txt
deahub.egg-info/top_level.txt
dist/CCR.py
dist/CCR_pyomo.py
dist/DDF.py
dist/DDF_pyomo.py
dist/SBM.py
dist/SBM_pyomo.py
dist/Ui_table.py
dist/__init__.py
dist/__main__.py
dist/deasolver.py
dist/pytransform_bootstrap.py
dist/pytransform_protection.py
dist/run.py
dist/pytransform/__init__.py
dist/pytransform/_pytransform.dll