Metadata-Version: 2.1
Name: deahub
Version: 1.0.0
Summary: Data envelopment analysis efficiency calculator
Home-page: https://github.com/DEATien
Author: WANGY
Author-email: wangy_prince@126.com
License: UNKNOWN
Platform: UNKNOWN
Classifier: Programming Language :: Python :: 3.7
Classifier: Operating System :: Microsoft :: Windows
Classifier: License :: OSI Approved :: GNU Affero General Public License v3 or later (AGPLv3+)
Classifier: Programming Language :: Python :: 3.8
Classifier: Operating System :: MacOS
Classifier: Programming Language :: Python :: 3.9
Classifier: Programming Language :: Python :: 3.6
Requires-Python: <3.10
